send_email.py
setup.py
t.py
send_email.egg-info/PKG-INFO
send_email.egg-info/SOURCES.txt
send_email.egg-info/dependency_links.txt
send_email.egg-info/top_level.txt